flask_shoppingcart/__init__.py
flask_shoppingcart/_shoppingcart.py
flask_shoppingcart/config.py
flask_shoppingcart/exceptions.py
flask_shoppingcart/flask_shoppingcart.py
flask_shoppingcart/manage_cart_item_extra_data.py
flask_shoppingcart/models.py
flask_shoppingcart/utils.py
flask_shoppingcart-0.4.0.dist-info/licenses/LICENCE
flask_shoppingcart-0.4.0.dist-info/METADATA
flask_shoppingcart-0.4.0.dist-info/WHEEL
flask_shoppingcart-0.4.0.dist-info/top_level.txt
flask_shoppingcart-0.4.0.dist-info/RECORD
