Metadata-Version: 2.4
Name: flask_shoppingcart
Version: 0.4.0
Summary: Add a shopping cart to your Flask app
Home-page: https://github.com/Brixt18/flask-shoppingcart
Author: Brixt18
Author-email: 
Maintainer: Brixt18
Classifier: Development Status :: 2 - Pre-Alpha
Classifier: Environment :: Web Environment
Classifier: Intended Audience :: Developers
Classifier: License :: OSI Approved :: BSD License
Classifier: Operating System :: OS Independent
Classifier: Programming Language :: Python
Classifier: Topic :: Internet :: WWW/HTTP :: Dynamic Content
Classifier: Typing :: Typed
Requires-Python: >=3.9
License-File: LICENCE
Requires-Dist: flask>=3.0
Dynamic: author
Dynamic: home-page
Dynamic: license-file
